GameStarter/__init__.py
GameStarter/gamestart_test.py
game_starter-2.0.0.dist-info/LICENSE
game_starter-2.0.0.dist-info/METADATA
game_starter-2.0.0.dist-info/WHEEL
game_starter-2.0.0.dist-info/top_level.txt
game_starter-2.0.0.dist-info/RECORD
