Metadata-Version: 2.1
Name: game-starter
Version: 2.0.0
Summary: Decides when to start a game, based on who's holding a button.
Home-page: https://github.com/danieljabailey/GameStarter
Author: Daniel Bailey, Nick Moriarty
Author-email: danieljabailey@gmail.com
License: UNKNOWN
Platform: UNKNOWN
Classifier: Programming Language :: Python :: 3
Classifier: License :: OSI Approved :: MIT License
Classifier: Operating System :: OS Independent
